{
  "name": "Intermediate Crochet Quiz",
  "description": "US vs UK terms and complex stitches",
  "total_questions": 42,
  "total_points": 210,
  "questions": [
    {
      "id": "uk_SC",
      "type": "terminology",
      "category": "US_vs_UK",
      "difficulty": "Intermediate",
      "question": "What is the UK term for 'Single Crochet'?",
      "answer": "Double Crochet",
      "term_id": "SC",
      "points": 5
    },
    {
      "id": "uk_HDC",
      "type": "terminology",
      "category": "US_vs_UK",
      "difficulty": "Intermediate",
      "question": "What is the UK term for 'Half Double Crochet'?",
      "answer": "Half Treble Crochet",
      "term_id": "HDC",
      "points": 5
    },
    {
      "id": "uk_DC",
      "type": "terminology",
      "category": "US_vs_UK",
      "difficulty": "Intermediate",
      "question": "What is the UK term for 'Double Crochet'?",
      "answer": "Treble Crochet",
      "term_id": "DC",
      "points": 5
    },
    {
      "id": "uk_TR",
      "type": "terminology",
      "category": "US_vs_UK",
      "difficulty": "Intermediate",
      "question": "What is the UK term for 'Treble Crochet'?",
      "answer": "Double Treble Crochet",
      "term_id": "TR",
      "points": 5
    },
    {
      "id": "uk_SC2TOG",
      "type": "terminology",
      "category": "US_vs_UK",
      "difficulty": "Intermediate",
      "question": "What is the UK term for 'Single Crochet Two Together'?",
      "answer": "Double Crochet Two Together",
      "term_id": "SC2TOG",
      "points": 5
    },
    {
      "id": "uk_DC2TOG",
      "type": "terminology",
      "category": "US_vs_UK",
      "difficulty": "Intermediate",
      "question": "What is the UK term for 'Double Crochet Two Together'?",
      "answer": "Treble Crochet Two Together",
      "term_id": "DC2TOG",
      "points": 5
    },
    {
      "id": "uk_FSC",
      "type": "terminology",
      "category": "US_vs_UK",
      "difficulty": "Intermediate",
      "question": "What is the UK term for 'Foundation Single Crochet'?",
      "answer": "Foundation Double Crochet",
      "term_id": "FSC",
      "points": 5
    },
    {
      "id": "uk_FHDC",
      "type": "terminology",
      "category": "US_vs_UK",
      "difficulty": "Intermediate",
      "question": "What is the UK term for 'Foundation Half Double Crochet'?",
      "answer": "Foundation Half Treble",
      "term_id": "FHDC",
      "points": 5
    },
    {
      "id": "uk_FPDC",
      "type": "terminology",
      "category": "US_vs_UK",
      "difficulty": "Intermediate",
      "question": "What is the UK term for 'Front Post Double Crochet'?",
      "answer": "Front Post Treble Crochet",
      "term_id": "FPDC",
      "points": 5
    },
    {
      "id": "uk_BPDC",
      "type": "terminology",
      "category": "US_vs_UK",
      "difficulty": "Intermediate",
      "question": "What is the UK term for 'Back Post Double Crochet'?",
      "answer": "Back Post Treble Crochet",
      "term_id": "BPDC",
      "points": 5
    },
    {
      "id": "uk_FPTR",
      "type": "terminology",
      "category": "US_vs_UK",
      "difficulty": "Intermediate",
      "question": "What is the UK term for 'Front Post Treble Crochet'?",
      "answer": "Front Post Double Treble",
      "term_id": "FPTR",
      "points": 5
    },
    {
      "id": "uk_BPTR",
      "type": "terminology",
      "category": "US_vs_UK",
      "difficulty": "Intermediate",
      "question": "What is the UK term for 'Back Post Treble Crochet'?",
      "answer": "Back Post Double Treble",
      "term_id": "BPTR",
      "points": 5
    },
    {
      "id": "uk_XST",
      "type": "terminology",
      "category": "US_vs_UK",
      "difficulty": "Intermediate",
      "question": "What is the UK term for 'Crossed Double Crochet'?",
      "answer": "Crossed Treble Crochet",
      "term_id": "XST",
      "points": 5
    },
    {
      "id": "uk_EXDC",
      "type": "terminology",
      "category": "US_vs_UK",
      "difficulty": "Intermediate",
      "question": "What is the UK term for 'Extended Double Crochet'?",
      "answer": "Extended Treble Crochet",
      "term_id": "EXDC",
      "points": 5
    },
    {
      "id": "uk_MOSS",
      "type": "terminology",
      "category": "US_vs_UK",
      "difficulty": "Intermediate",
      "question": "What is the UK term for 'Moss Stitch'?",
      "answer": "Linen Stitch",
      "term_id": "MOSS",
      "points": 5
    },
    {
      "id": "uk_WW",
      "type": "terminology",
      "category": "US_vs_UK",
      "difficulty": "Intermediate",
      "question": "What is the UK term for 'Worsted Weight'?",
      "answer": "Aran Weight",
      "term_id": "WW",
      "points": 5
    },
    {
      "id": "uk_GAUGE",
      "type": "terminology",
      "category": "US_vs_UK",
      "difficulty": "Intermediate",
      "question": "What is the UK term for 'Gauge'?",
      "answer": "Tension",
      "term_id": "GAUGE",
      "points": 5
    },
    {
      "id": "uk_SK",
      "type": "terminology",
      "category": "US_vs_UK",
      "difficulty": "Intermediate",
      "question": "What is the UK term for 'Skip'?",
      "answer": "Miss",
      "term_id": "SK",
      "points": 5
    },
    {
      "id": "uk_DTR",
      "type": "terminology",
      "category": "US_vs_UK",
      "difficulty": "Intermediate",
      "question": "What is the UK term for 'Double Treble Crochet'?",
      "answer": "Triple Treble Crochet",
      "term_id": "DTR",
      "points": 5
    },
    {
      "id": "uk_TRTR",
      "type": "terminology",
      "category": "US_vs_UK",
      "difficulty": "Intermediate",
      "question": "What is the UK term for 'Triple Treble Crochet'?",
      "answer": "Quadruple Treble Crochet",
      "term_id": "TRTR",
      "points": 5
    },
    {
      "id": "uk_YO",
      "type": "terminology",
      "category": "US_vs_UK",
      "difficulty": "Intermediate",
      "question": "What is the UK term for 'Yarn Over'?",
      "answer": "Yarn Over Hook",
      "term_id": "YO",
      "points": 5
    },
    {
      "id": "uk_WEAVE",
      "type": "terminology",
      "category": "US_vs_UK",
      "difficulty": "Intermediate",
      "question": "What is the UK term for 'Weave in Ends'?",
      "answer": "Sew in Ends",
      "term_id": "WEAVE",
      "points": 5
    },
    {
      "id": "uk_BO",
      "type": "terminology",
      "category": "US_vs_UK",
      "difficulty": "Intermediate",
      "question": "What is the UK term for 'Bind Off'?",
      "answer": "Cast Off",
      "term_id": "BO",
      "points": 5
    },
    {
      "id": "uk_TBO",
      "type": "terminology",
      "category": "US_vs_UK",
      "difficulty": "Intermediate",
      "question": "What is the UK term for 'Tunisian Bind Off'?",
      "answer": "Tunisian Cast Off",
      "term_id": "TBO",
      "points": 5
    },
    {
      "id": "uk_TCOLOR",
      "type": "terminology",
      "category": "US_vs_UK",
      "difficulty": "Intermediate",
      "question": "What is the UK term for 'Tunisian Color Change'?",
      "answer": "Tunisian Colour Change",
      "term_id": "TCOLOR",
      "points": 5
    }
  ]
}